README.md
setup.py
Sizzler.egg-info/PKG-INFO
Sizzler.egg-info/SOURCES.txt
Sizzler.egg-info/dependency_links.txt
Sizzler.egg-info/entry_points.txt
Sizzler.egg-info/requires.txt
Sizzler.egg-info/top_level.txt
sizzler/__init__.py
sizzler/__main__.py
sizzler/tun.py
sizzler/config/__init__.py
sizzler/config/parser.py
sizzler/crypto/__init__.py
sizzler/crypto/crypto.py
sizzler/crypto/padding.py
sizzler/transport/__init__.py
sizzler/transport/_transport.py
sizzler/transport/_wssession.py
sizzler/transport/router.py
sizzler/transport/wsclient.py
sizzler/transport/wsserver.py
sizzler/util/__init__.py
sizzler/util/cmdline.py
sizzler/util/root.py