Metadata-Version: 1.0
Name: Sizzler
Version: 0.0.2
Summary: A VPN over WebSocket
Home-page: http://github.com/scmagi/sizzler
Author: Sogisha
Author-email: sogisha@protonmail.com
License: MIT
Keywords: asyncio VPN WebSocket TUN
Platform: UNKNOWN
